{
  "objectInfo" : {
    "id" : "0WVPFqxVe4udQNrpB5laIU",
    "name" : "Amqp_direct - Copy 1 - Copy 1",
    "type" : "SIDataflow",
    "metadata" : {
      "modelVersion" : {
        "major" : 0,
        "minor" : 0
      },
      "repoInfo" : {
        "repoHandle" : "16fa7f79-a942-41b6-af16-16d20488d63a"
      },
      "contextAttributes" : [ {
        "name" : "parentId",
        "value" : "97efNeOvfCwdUgVtbb1g2G"
      }, {
        "name" : "version",
        "value" : "1"
      } ],
      "additionalInfo" : {
        "description" : null,
        "contentType" : null,
        "documentState" : "COMPLETE"
      }
    }
  },
  "dataFileExtension" : "dat",
  "objectRefs" : [ {
    "id" : "4nPYcbGkloubJDwsZ92bs2",
    "name" : "INubuntu02",
    "type" : "AgentGroup",
    "metadata" : {
      "modelVersion" : {
        "major" : 0,
        "minor" : 0
      },
      "repoInfo" : {
        "repoHandle" : "010NWA25000000000002"
      },
      "contextAttributes" : null,
      "additionalInfo" : {
        "description" : null,
        "contentType" : "JSON",
        "documentState" : "VALID"
      }
    },
    "path" : "/SYS"
  }, {
    "id" : "3MGImXA9346kIGJXcpaLII",
    "name" : "Amqp_direct",
    "type" : "Connection",
    "metadata" : {
      "modelVersion" : {
        "major" : 0,
        "minor" : 0
      },
      "repoInfo" : {
        "repoHandle" : "010NWA0B000000000002"
      },
      "contextAttributes" : null,
      "additionalInfo" : {
        "description" : null,
        "contentType" : "JSON",
        "documentState" : "COMPLETE"
      }
    },
    "path" : "/SYS"
  }, {
    "id" : "cRHWaL0dxoqfoHotdSHPIA",
    "name" : "Kafka",
    "type" : "Connection",
    "metadata" : {
      "modelVersion" : {
        "major" : 0,
        "minor" : 0
      },
      "repoInfo" : {
        "repoHandle" : "010NWA0B000000000005"
      },
      "contextAttributes" : null,
      "additionalInfo" : {
        "description" : null,
        "contentType" : "JSON",
        "documentState" : "COMPLETE"
      }
    },
    "path" : "/SYS"
  } ]
}